nlptkl/__init__.py
nlptkl/loader.py
nlptkl/data/sample1.txt
nlptkl/data/streamlitx.txt
nlptkl_zxc-0.2.0.dist-info/LICENSE
nlptkl_zxc-0.2.0.dist-info/METADATA
nlptkl_zxc-0.2.0.dist-info/WHEEL
nlptkl_zxc-0.2.0.dist-info/top_level.txt
nlptkl_zxc-0.2.0.dist-info/RECORD
