Metadata-Version: 2.1
Name: nlptkl-zxc
Version: 0.2.0
Summary: A simple library that serves bundled text files.
Author-email: Your Name <your@email.com>
License: MIT
Requires-Python: >=3.8
License-File: LICENSE
